{"cameraMode":{"drawMode":0,"name":"Shaded","section":"Shading Mode"},"sceneLighting":true,"audioPlay":false,"sceneViewState":{"m_AlwaysRefresh":false,"showFog":true,"showSkybox":true,"showFlares":true,"showImageEffects":true,"showParticleSystems":true,"showVisualEffectGraphs":true,"m_FxEnabled":true},"in2DMode":false,"pivot":{"x":0.8961238861083984,"y":-2.311988115310669,"z":5.5026535987854},"rotation":{"x":0.7071068286895752,"y":0.0,"z":0.0,"w":0.7071068286895752},"size":44.76426696777344,"orthographic":false}